vector_nest/__init__.py
vector_nest-0.1.1.dist-info/LICENSE
vector_nest-0.1.1.dist-info/METADATA
vector_nest-0.1.1.dist-info/WHEEL
vector_nest-0.1.1.dist-info/top_level.txt
vector_nest-0.1.1.dist-info/RECORD
