Metadata-Version: 2.1
Name: vector-nest
Version: 0.1.1
Summary: A package for text similarity and embeddings
Home-page: https://github.com/sairam-penjarla/vector_nest.git
Author: Penjarla Sai Ram
Author-email: psairam9301@gmail.com
Classifier: Programming Language :: Python :: 3
Classifier: License :: OSI Approved :: MIT License
Classifier: Operating System :: OS Independent
License-File: LICENSE
Requires-Dist: numpy
Requires-Dist: scikit-learn
Requires-Dist: sentence-transformers
